chameleon/__init__.py
chameleon/astutil.py
chameleon/benchmark.py
chameleon/codegen.py
chameleon/compiler.py
chameleon/config.py
chameleon/exc.py
chameleon/i18n.py
chameleon/loader.py
chameleon/metal.py
chameleon/namespaces.py
chameleon/nodes.py
chameleon/parser.py
chameleon/program.py
chameleon/py.typed
chameleon/tal.py
chameleon/tales.py
chameleon/template.py
chameleon/tokenize.py
chameleon/types.py
chameleon/utils.py
chameleon/zpt/__init__.py
chameleon/zpt/loader.py
chameleon/zpt/program.py
chameleon/zpt/template.py
Chameleon-4.5.4.dist-info/LICENSE.txt
Chameleon-4.5.4.dist-info/METADATA
Chameleon-4.5.4.dist-info/WHEEL
Chameleon-4.5.4.dist-info/top_level.txt
Chameleon-4.5.4.dist-info/RECORD
