Metadata-Version: 2.1
Name: Chameleon
Version: 4.5.4
Summary: Fast HTML/XML Template Compiler.
Home-page: https://chameleon.readthedocs.io
Author: Malthe Borch
Author-email: mborch@gmail.com
License: BSD-like (http://repoze.org/license.html)
Project-URL: Documentation, https://chameleon.readthedocs.io
Project-URL: Issue Tracker, https://github.com/malthe/chameleon/issues
Project-URL: Sources, https://github.com/malthe/chameleon
Platform: UNKNOWN
Classifier: Development Status :: 5 - Production/Stable
Classifier: Intended Audience :: Developers
Classifier: Programming Language :: Python
Classifier: Programming Language :: Python :: 3
Classifier: Programming Language :: Python :: 3.9
Classifier: Programming Language :: Python :: 3.10
Classifier: Programming Language :: Python :: 3.11
Classifier: Programming Language :: Python :: 3.12
Classifier: Programming Language :: Python :: 3.13
Classifier: Programming Language :: Python :: Implementation :: CPython
Classifier: Programming Language :: Python :: Implementation :: PyPy
Requires-Python: >=3.9
Provides-Extra: docs
License-File: LICENSE.txt
